m16_mlutils/__init__.py
m16_mlutils/datatools/DataDescription.py
m16_mlutils/datatools/__init__.py
m16_mlutils/datatools/evaluation.py
m16_mlutils/pipeline/CategoryEncoder.py
m16_mlutils/pipeline/DataFrameSelector.py
m16_mlutils/pipeline/MostFrequentImputer.py
m16_mlutils/pipeline/__init__.py
m16_mlutils/plot/__init__.py
m16_mlutils/plot/confusion_matrix.py
m16_mlutils/plot/utils.py
tests/NumPyTestCase.py
tests/__init__.py
tests/test_CategoryEncoder.py
tests/test_DataDescription.py
tests/test_DataFrameSelector.py
tests/test_IntegrationWithPipeline.py
tests/test_MostFrequentImputer.py
tests/test_evaluation.py
tests/plot/__init__.py
tests/plot/test_utils.py
m16_mlutils-0.7.1.dist-info/LICENSE
m16_mlutils-0.7.1.dist-info/METADATA
m16_mlutils-0.7.1.dist-info/WHEEL
m16_mlutils-0.7.1.dist-info/top_level.txt
m16_mlutils-0.7.1.dist-info/RECORD
