Metadata-Version: 2.1
Name: m16-mlutils
Version: 0.7.1
Summary: Some stuff that is probably better implemented somewhere else but I'm still a newbie to find out where...
Home-page: https://github.com/messier16/m16_mlutils
Author: Antonio Feregrino
Author-email: antonio.feregrino@gmail.com
License: UNKNOWN
Platform: UNKNOWN
Classifier: Programming Language :: Python :: 3
Classifier: License :: OSI Approved :: MIT License
Classifier: Operating System :: OS Independent
